raspi_system/__init__.py
raspi_system/hwinfo.py
raspi_system/network.py
raspi_system-0.1.1.dist-info/METADATA
raspi_system-0.1.1.dist-info/WHEEL
raspi_system-0.1.1.dist-info/top_level.txt
raspi_system-0.1.1.dist-info/RECORD
